[null,{"name":"test","permissions":"ADMINISTRATOR","restriction":"1","actions":[{"gameName":"HaZe | Copyright 2020","gameLink":"","name":"Set Bot Game"}]},{"name":"haze-info","permissions":"SEND_MESSAGES","restriction":"1","actions":[{"title":"HaZe Esport | Informace","author":"renyS","color":"#ff5050","timestamp":"true","url":"https://steamcommunity.com/groups/HaZeCZE","authorIcon":"","imageUrl":"","thumbUrl":"","storage":"1","varName":"Informace","name":"Create Embed Message"},{"storage":"1","varName":"Informace","fieldName":"Informace","message":"Esport Gaming | HaZe \nZaměřený pouze na CS:GO, jelikož jsme od 2020.\nTak samozřejmě dokážeme i nemožné. A jsme připraveni na ty nejlepší soupeře.\nJelikož jsme nový tým, dokážeme i nabrat hráče co jsou schopný a mají určitý daný\nTrustFactor a Rank!","inline":"1","name":"Add Embed Field"},{"storage":"1","varName":"Informace","channel":"0","varName2":"","name":"Send Embed Message"},{"storage":"0","varName":"","permission":"MANAGE_CHANNELS","state":"0","name":"Set Channel Permissions"},{"info":"0","find":"710112411725725696","storage":"1","varName":"haze-info","name":"Find Channel"}]},{"name":"NewCommand","permissions":"NONE","restriction":"1","actions":[]}]